csv2pg/__init__.py
csv2pg/cli.py
csv2pg/exceptions.py
csv2pg/main.py
csv2pg/striter.py
csv2pg-2.2.0.dist-info/LICENSE
csv2pg-2.2.0.dist-info/METADATA
csv2pg-2.2.0.dist-info/WHEEL
csv2pg-2.2.0.dist-info/entry_points.txt
csv2pg-2.2.0.dist-info/top_level.txt
csv2pg-2.2.0.dist-info/RECORD
