Metadata-Version: 2.1
Name: csv2pg
Version: 2.2.0
Summary: A simple and fast cli application to load a csv into postgres
Home-page: https://github.com/DavidLacroix/csv2pg
Author: David Lacroix
License: UNKNOWN
Keywords: postgres csv
Platform: UNKNOWN
Classifier: Development Status :: 5 - Production/Stable
Classifier: Intended Audience :: Developers
Classifier: License :: OSI Approved :: GNU General Public License v3 (GPLv3)
Classifier: Programming Language :: Python :: 3
Requires-Python: >=3.5
Requires-Dist: Click
Requires-Dist: psycopg2-binary (>=2.0.6)
Requires-Dist: tqdm
